Workbook

Sheet Сотрудники
A1: ID | B1: ФИО | C1: Должность/Грейд | D1: Дата рождения | E1: Гороскоп:) | F1: Телефон | G1: Email | H1: Дата найма | I1: Статус
A2: 1 | B2: Россинский Вадим Олегович | C2: Менеджер по продажам | D2: 35142 | E2: Рыбы | F2: 79641114795 | G2: ivanov@company.ru | H2: 45743 | I2: Активен
A3: 2 | B3: Федосеев Максим Андреевич | C3: Менеджер по продажам | D3: 36077 | E3: Весы | F3: 79642252741 | G3: petrova@company.ru | H3: 45818 | I3: Активен
A4: 3 | B4: Фёдорова Анастасия Андреевна | C4: Младший менеджер | D4: 34442 | E4: Овен | F4: 79041461842 | G4: sidorov@company.ru | H4: 46136 | I4: Активен
A5: 4 | B5: Багланова Антонина Михайловна | C5: Старший менеджер по продажам | D5: 33255 | E5: Козерог | F5: 79501122687 | G5: kuznetsova@company.ru | H5: 45894 | I5: Активен
A6: 5 | B6: Соболев Максим Андреевич | C6: Старший менеджер по продажам | D6: 36273 | E6: Овен | F6: 79149309554 | G6: morozov@company.ru | H6: 2023 | I6: Активен
A7: 6 | B7: Савинская Евгения Николаевна | C7: Тимлид | D7: 34212 | E7: Дева | F7: 79246349906 | H7: 43556 | I7: Активен

Sheet Зарплата
A1: ID | B1: ФИО | C1: Оклад (руб) | D1: Базовый процент от продаж (%) | E1: План продаж (руб/мес) | F1: КПИ | G1: Доп. бонусы | H1: Общий доход (прогноз, руб)
A2: 1 | B2: Россинский Вадим Олегович | E2: 350000
A3: 2 | B3: Федосеев Максим Андреевич | E3: 350000
A4: 3 | B4: Фёдорова Анастасия Андреевна | E4: 150000
A5: 4 | B5: Багланова Антонина Михайловна | E5: 350000
A6: 5 | B6: Соболев Максим Андреевич | E6: 350000
A7: 6 | B7: Савинская Евгения Николаевна | C7: 72000 | D7: 1 | E7: =SUM(E2:E6) -> 1550000
A15: ID | B15: ФИО | C15: План МД | D15: Выполнение плана ср МД | E15: % выполнения плана МД | F15: Средний чек (руб) | G15: Звонки (в день) | H15: Встречи (в неделю) | I15: Оценка качества звонков | J15: Рейтинг в команде
A16: 1 | B16: Россинский Вадим Олегович | C16: 320000 | D16: =AVERAGE('МД и эффективность 2026'!C6,'МД и эффективность 2026'!F6,'МД и эффективность 2026'!J6,'МД и эффективность 2026'!M6,'МД и эффективность 2026'!P6,'МД и эффективность 2026'!S6,'МД и эффективность 2026'!C13) -> 295486.43
A17: 2 | B17: Федосеев Максим Андреевич | C17: 320000 | D17: =AVERAGE('МД и эффективность 2026'!C7,'МД и эффективность 2026'!F7,'МД и эффективность 2026'!J7,'МД и эффективность 2026'!M7,'МД и эффективность 2026'!P7,'МД и эффективность 2026'!S7,'МД и эффективность 2026'!C14) -> 244627.43
A18: 3 | B18: Фёдорова Анастасия Андреевна | C18: 50000 | D18: =AVERAGE('МД и эффективность 2026'!C8,'МД и эффективность 2026'!F8,'МД и эффективность 2026'!J8,'МД и эффективность 2026'!M8,'МД и эффективность 2026'!P8,'МД и эффективность 2026'!S8,'МД и эффективность 2026'!C15) -> 100565
A19: 4 | B19: Багланова Антонина Михайловна | C19: 350000 | D19: =AVERAGE('МД и эффективность 2026'!C4,'МД и эффективность 2026'!F4,'МД и эффективность 2026'!J4,'МД и эффективность 2026'!M4,'МД и эффективность 2026'!P4,'МД и эффективность 2026'!S4,'МД и эффективность 2026'!C11,'МД и эффективность 2026'!F11,'МД и эффективность 2026'!J11,'МД и эффективность 2026'!M11,'МД и эффективность 2026'!P11,'МД и эффективность 2026'!S11) -> 124619
A20: 5 | B20: Соболев Максим Андреевич | C20: 350000 | D20: =AVERAGE('МД и эффективность 2026'!C5,'МД и эффективность 2026'!F5,'МД и эффективность 2026'!J5,'МД и эффективность 2026'!M5,'МД и эффективность 2026'!P5,'МД и эффективность 2026'!S5,'МД и эффективность 2026'!C12) -> 353814
A21: 6 | B21: Савинская Евгения Николаевна

Sheet тест
A2: МД
B3: МПП | C3: январь | D3: % | E3: нк | F3: февраль | G3: % | H3: нк | I3: март | J3: % | K3: нк | L3: апрель | M3: % | N3: нк | O3: май | P3: % | Q3: нк | R3: июнь | S3: % | T3: нк
A4: 350000 | B4: Багланова | C4: 156374 | D4: =C4/350000*100% -> 0.44678286 | E4: 7 | F4: 129868 | G4: =F4/350000*100% -> 0.37105143 | H4: 2 | I4: 88587 | J4: =I4/350000*100% -> 0.25310571 | K4: 4 | L4: 89000 | M4: =L4/A4*100% -> 0.25428571 | N4: 7 | O4: 127625 | P4: =O4/A4*100% -> 0.36464286 | Q4: 4 | R4: 147020 | S4: =R4/A4*100% -> 0.42005714 | T4: 4
A5: 350000 | B5: Соболев | C5: 437270 | D5: =C5/350000*100% -> 1.2493429 | E5: 19 | F5: 336283 | G5: =F5/350000*100% -> 0.96080857 | H5: 12 | I5: 438973 | J5: =I5/350000*100% -> 1.2542086 | K5: 14 | L5: 160000 | M5: =L5/A5*100% -> 0.45714286 | N5: 3 | O5: 262000 | P5: =O5/A5*100% -> 0.74857143 | Q5: 4 | R5: 466583 | S5: =R5/A5*100% -> 1.3330943 | T5: 10
A6: 320000 | B6: Россинский | C6: 245527 | D6: =C6/320000*100% -> 0.76727188 | E6: 13 | F6: 343570 | G6: =F6/320000*100% -> 1.0736562 | H6: 12 | I6: 176445 | J6: =I6/320000*100% -> 0.55139063 | K6: 8 | L6: 202082 | M6: =L6/A6*100% -> 0.63150625 | N6: 7 | O6: 424127 | P6: =O6/A6*100% -> 1.3253969 | Q6: 9 | R6: 334011 | S6: =R6/A6*100% -> 1.0437844 | T6: 6
A7: 320000 | B7: Федосеев | C7: 144032 | D7: =C7/320000*100% -> 0.4501 | E7: 7 | F7: 145716 | G7: =F7/320000*100% -> 0.4553625 | H7: 2 | I7: 92434 | J7: =I7/320000*100% -> 0.28885625 | K7: 4 | L7: 143686 | M7: =L7/A7*100% -> 0.44901875 | N7: 9 | O7: 190159 | P7: =O7/A7*100% -> 0.59424687 | Q7: 4 | R7: 220749 | S7: =R7/A7*100% -> 0.68984062 | T7: 6
A8: 150000 | B8: Фёдорова
B10: МПП | C10: июль | D10: % | E10: нк | F10: август | G10: % | H10: нк | I10: сентябрь | J10: % | K10: нк | L10: октябрь | M10: % | N10: нк | O10: ноябрь | P10: % | Q10: нк | R10: декабрь | S10: % | T10: нк
A11: 350000 | B11: Багланова | C11: 171961 | D11: =C11/350000*100% -> 0.49131714 | E11: 6
A12: 350000 | B12: Соболев | C12: 375589 | D12: =C12/350000*100% -> 1.0731114
A13: 320000 | B13: Россинский | C13: 342643 | D13: =C13/320000*100% -> 1.0707594 | E13: 7
A14: 320000 | B14: Федосеев | C14: 775616 | D14: =C14/320000*100% -> 2.4238 | E14: 5
A15: 150000 | B15: Фёдорова | C15: 100565 | D15: =C15/50000*100% -> 2.0113 | E15: 0
A18: Сделки и конверсия | L18: Самая низкая конверсия | M18: 0.253 | N18: 46204
B19: МПП | C19: месяц | D19: колич сделок (шт) | E19: колич усп.сд (шт) | F19: конв из сделки в оплату % | G19: отклонение | M19: Источники | N19: количество | O19: причина отвала | P19: Этап отвала
B20: Багланова | C20: январь | D20: 69 | E20: 15 | F20: =E20/D20*100% -> 0.2173913 | M20: свой контакт | N20: 22
B21: Соболев | D21: 161 | E21: 54 | F21: =E21/D21*100% -> 0.33540373 | M21: звонок | N21: 23
B22: Россинский | D22: 85 | E22: 21 | F22: =E22/D22*100% -> 0.24705882 | M22: холодный обзвон | N22: 2
B23: Федосеев | D23: 123 | E23: 21 | F23: =E23/D23*100% -> 0.17073171 | M23: мероприятия Форус | N23: 1
B24: Багланова | C24: февраль | D24: 41 | E24: 9 | F24: =E24/D24*100% -> 0.2195122 | G24: =F24-F20 -> 0.0021208908 | M24: успешная регистрация | N24: 46 | P24: Необработанные, уточнить потребности
B25: Соболев | D25: 110 | E25: 36 | F25: =E25/D25*100% -> 0.32727273 | G25: =F25-F21 -> -0.0081309994 | M25: сайт итс | N25: 5
B26: Россинский | D26: 64 | E26: 37 | F26: =E26/D26*100% -> 0.578125 | G26: =F26-F22 -> 0.33106618 | M26: по рекомендации | N26: 7
B27: Федосеев | D27: 86 | E27: 15 | F27: =E27/D27*100% -> 0.1744186 | G27: =F27-F23 -> 0.0036868973 | M27: срм форма | N27: 11
B28: Багланова | C28: март | D28: 43 | E28: 18 | F28: =E28/D28*100% -> 0.41860465 | G28: =F28-F24 -> 0.19909246 | M28: лендинг 1С | N28: 1
B29: Соболев | D29: 97 | E29: 31 | F29: =E29/D29*100% -> 0.31958763 | G29: =F29-F25 -> -0.0076850984 | M29: квиз | N29: 3
B30: Россинский | D30: 63 | E30: 29 | F30: =E30/D30*100% -> 0.46031746 | G30: =F30-F26 -> -0.11780754 | M30: авито | N30: 5
B31: Федосеев | D31: 53 | E31: 11 | F31: =E31/D31*100% -> 0.20754717 | G31: =F31-F27 -> 0.033128565 | M31: регулярная сделка(Возврат Фреш, КП + продление каспера) | N31: 35 | O31: дубль,1с не пользуется , подключили тестовый, финанс.сложн,приостановка деятельности, перешли на аутсорс, ушел к др.партнеру, проблемы с согласованием | P31: необработанные, контроль сделки , отправить счет
B32: Багланова | C32: апрель | D32: 72 | E32: 20 | F32: =E32/D32*100% -> 0.27777778 | G32: =F32-F28 -> -0.14082687
B33: Соболев | D33: 124 | E33: 32 | F33: =E33/D33*100% -> 0.25806452 | G33: =F33-F29 -> -0.061523113
B34: Россинский | D34: 91 | E34: 34 | F34: =E34/D34*100% -> 0.37362637 | G34: =F34-F30 -> -0.086691087
B35: Федосеев | D35: 79 | E35: 25 | F35: =E35/D35*100% -> 0.3164557 | G35: =F35-F31 -> 0.10890853
B36: Багланова | C36: май | D36: 37 | E36: 9 | F36: =E36/D36*100% -> 0.24324324 | G36: =F36-F32 -> -0.034534535
B37: Соболев | D37: 84 | E37: 36 | F37: =E37/D37*100% -> 0.42857143 | G37: =F37-F33 -> 0.17050691
B38: Россинский | D38: 37 | E38: 17 | F38: =E38/D38*100% -> 0.45945946 | G38: =F38-F34 -> 0.085833086
B39: Федосеев | D39: 40 | E39: 6 | F39: =E39/D39*100% -> 0.15 | G39: =F39-F35 -> -0.1664557
B40: Багланова | C40: июнь | D40: 56 | E40: 24 | F40: =E40/D40*100% -> 0.42857143 | G40: =F40-F36 -> 0.18532819
B41: Соболев | D41: 88 | E41: 36 | F41: =E41/D41*100% -> 0.40909091 | G41: =F41-F37 -> -0.019480519
B42: Россинский | D42: 60 | E42: 28 | F42: =E42/D42*100% -> 0.46666667 | G42: =F42-F38 -> 0.0072072072
B43: Федосеев | D43: 52 | E43: 14 | F43: =E43/D43*100% -> 0.26923077 | G43: =F43-F39 -> 0.11923077
B44: Багланова | C44: июль | D44: 42 | E44: 16 | F44: =E44/D44*100% -> 0.38095238 | G44: =F44-F40 -> -0.047619048
B45: Соболев | D45: 67 | E45: 16 | F45: =E45/D45*100% -> 0.23880597 | G45: =F45-F41 -> -0.17028494
B46: Россинский | D46: 95 | E46: 24 | F46: =E46/D46*100% -> 0.25263158 | G46: =F46-F42 -> -0.21403509
B47: Фёдорова | D47: 70 | E47: 19 | F47: =E47/D47*100% -> 0.27142857 | G47: =F47-F43 -> 0.0021978022
B48: Федосеев | D48: 90 | E48: 17 | F48: =E48/D48*100% -> 0.18888889 | G48: =F48-F44 -> -0.19206349
B49: Багланова | C49: август
B50: Соболев
B51: Россинский
B52: Федосеев
B53: Багланова | C53: сентябрь
B54: Соболев
B55: Россинский
B56: Федосеев | I56: конверсия из сд в оплату %
B57: Багланова | C57: октябрь | I57: =AVERAGE(F20:F48) -> 0.31342885
B58: Соболев
B59: Россинский
B60: Федосеев
B61: Багланова | C61: ноябрь
B62: Соболев
B63: Россинский
B64: Федосеев
B65: Багланова | C65: декабрь
B66: Соболев
B67: Россинский
B68: Федосеев
B69: Всего сделок | D69: =SUM(D20:D48) -> 2179
B70: Успешные сделки | E70: =SUM(E20:E48) -> 670
B71: Сделки в работе | E71: 230
B72: Неусп.сделки | E72: 1318 | F72: =D69-E70-E71 -> 1279
B73: Ср.колич сд в мес | C73: 311
B74: Ср.колич Усп. Сд/ мес | C74: 96

Sheet МД и эффективность 2026
A2: МД
B3: МПП | C3: январь | D3: % | E3: нк | F3: февраль | G3: % | I3: нк | J3: март | K3: % | L3: нк | M3: апрель | N3: % | O3: нк | P3: май | Q3: % | R3: нк | S3: июнь | T3: % | U3: нк
A4: 350000 | B4: Багланова | C4: 156374 | D4: =C4/350000*100% -> 0.44678286 | E4: 7 | F4: 129868 | G4: =F4/350000*100% -> 0.37105143 | I4: 2 | J4: 88587 | K4: =J4/350000*100% -> 0.25310571 | L4: 4 | M4: 89000 | N4: =M4/A4*100% -> 0.25428571 | O4: 7 | P4: 127625 | Q4: =P4/A4*100% -> 0.36464286 | R4: 4 | S4: 147020 | T4: =S4/A4*100% -> 0.42005714 | U4: 4
A5: 350000 | B5: Соболев | C5: 437270 | D5: =C5/350000*100% -> 1.2493429 | E5: 19 | F5: 336283 | G5: =F5/350000*100% -> 0.96080857 | I5: 12 | J5: 438973 | K5: =J5/350000*100% -> 1.2542086 | L5: 14 | M5: 160000 | N5: =M5/A5*100% -> 0.45714286 | O5: 3 | P5: 262000 | Q5: =P5/A5*100% -> 0.74857143 | R5: 4 | S5: 466583 | T5: =S5/A5*100% -> 1.3330943 | U5: 10
A6: 320000 | B6: Россинский | C6: 245527 | D6: =C6/320000*100% -> 0.76727188 | E6: 13 | F6: 343570 | G6: =F6/320000*100% -> 1.0736562 | I6: 12 | J6: 176445 | K6: =J6/320000*100% -> 0.55139063 | L6: 8 | M6: 202082 | N6: =M6/A6*100% -> 0.63150625 | O6: 7 | P6: 424127 | Q6: =P6/A6*100% -> 1.3253969 | R6: 9 | S6: 334011 | T6: =S6/A6*100% -> 1.0437844 | U6: 6
A7: 320000 | B7: Федосеев | C7: 144032 | D7: =C7/320000*100% -> 0.4501 | E7: 7 | F7: 145716 | G7: =F7/320000*100% -> 0.4553625 | I7: 2 | J7: 92434 | K7: =J7/320000*100% -> 0.28885625 | L7: 4 | M7: 143686 | N7: =M7/A7*100% -> 0.44901875 | O7: 9 | P7: 190159 | Q7: =P7/A7*100% -> 0.59424687 | R7: 4 | S7: 220749 | T7: =S7/A7*100% -> 0.68984062 | U7: 6
A8: 150000 | B8: Фёдорова
B10: МПП | C10: июль | D10: % | E10: нк | F10: август | G10: % | I10: нк | J10: сентябрь | K10: % | L10: нк | M10: октябрь | N10: % | O10: нк | P10: ноябрь | Q10: % | R10: нк | S10: декабрь | T10: % | U10: нк
A11: 350000 | B11: Багланова | C11: 171961 | D11: =C11/350000*100% -> 0.49131714 | E11: 6 | F11: 86517 | G11: =F11/A11*100% -> 0.24719143 | I11: 1
A12: 350000 | B12: Соболев | C12: 375589 | D12: =C12/350000*100% -> 1.0731114 | E12: 4 | F12: 202857 | G12: =F12/A12*100% -> 0.57959143 | I12: 1
A13: 320000 | B13: Россинский | C13: 342643 | D13: =C13/320000*100% -> 1.0707594 | E13: 7 | F13: 334237 | G13: =F13/A13*100% -> 1.0444906 | I13: 10
A14: 200000 | B14: Федосеев | C14: 775616 | D14: =C14/320000*100% -> 2.4238 | E14: 5 | F14: 272821 | G14: =272821/200000*100% -> 1.364105 | I14: 8
A15: 150000 | B15: Фёдорова | C15: 100565 | D15: =C15/50000*100% -> 2.0113 | E15: 0 | F15: 155451 | G15: =F15/A15*100% -> 1.03634 | I15: 1
A18: Сделки и конверсия
B19: МПП | C19: месяц | D19: колич сделок (шт) | E19: колич усп.сд (шт) | F19: конв из сделки в оплату % | G19: отклонение | H19: Колич сд/мес | I19: Успешные сделки по группе | J19: Ср конверсия мес %
B20: Багланова | C20: январь | D20: 69 | E20: 15 | F20: =E20/D20*100% -> 0.2173913 | H20: =SUM(D20:D23) -> 438 | I20: =SUM(E20:E23) -> 111 | J20: =AVERAGE(F20:F23) -> 0.24264639
B21: Соболев | D21: 161 | E21: 54 | F21: =E21/D21*100% -> 0.33540373
B22: Россинский | D22: 85 | E22: 21 | F22: =E22/D22*100% -> 0.24705882
B23: Федосеев | D23: 123 | E23: 21 | F23: =E23/D23*100% -> 0.17073171
B24: Багланова | C24: февраль | D24: 41 | E24: 9 | F24: =E24/D24*100% -> 0.2195122 | G24: =F24-F20 -> 0.0021208908 | H24: =SUM(D24:D27) -> 301 | I24: =SUM(E24:E27) -> 97 | J24: =AVERAGE(F24:F28) -> 0.34358664
B25: Соболев | D25: 110 | E25: 36 | F25: =E25/D25*100% -> 0.32727273 | G25: =F25-F21 -> -0.0081309994
B26: Россинский | D26: 64 | E26: 37 | F26: =E26/D26*100% -> 0.578125 | G26: =F26-F22 -> 0.33106618
B27: Федосеев | D27: 86 | E27: 15 | F27: =E27/D27*100% -> 0.1744186 | G27: =F27-F23 -> 0.0036868973
B28: Багланова | C28: март | D28: 43 | E28: 18 | F28: =E28/D28*100% -> 0.41860465 | G28: =F28-F24 -> 0.19909246 | H28: =SUM(D28:D31) -> 256 | I28: =SUM(E28:E31) -> 89
B29: Соболев | D29: 97 | E29: 31 | F29: =E29/D29*100% -> 0.31958763 | G29: =F29-F25 -> -0.0076850984 | J29: =AVERAGE(F29:F33) -> 0.30465891
B30: Россинский | D30: 63 | E30: 29 | F30: =E30/D30*100% -> 0.46031746 | G30: =F30-F26 -> -0.11780754
B31: Федосеев | D31: 53 | E31: 11 | F31: =E31/D31*100% -> 0.20754717 | G31: =F31-F27 -> 0.033128565
B32: Багланова | C32: апрель | D32: 72 | E32: 20 | F32: =E32/D32*100% -> 0.27777778 | G32: =F32-F28 -> -0.14082687 | H32: =SUM(D32:D35) -> 366 | I32: =SUM(E32:E35) -> 111
B33: Соболев | D33: 124 | E33: 32 | F33: =E33/D33*100% -> 0.25806452 | G33: =F33-F29 -> -0.061523113
B34: Россинский | D34: 91 | E34: 34 | F34: =E34/D34*100% -> 0.37362637 | G34: =F34-F30 -> -0.086691087 | J34: =AVERAGE(F34:F38) -> 0.36427124
B35: Федосеев | D35: 79 | E35: 25 | F35: =E35/D35*100% -> 0.3164557 | G35: =F35-F31 -> 0.10890853
B36: Багланова | C36: май | D36: 37 | E36: 9 | F36: =E36/D36*100% -> 0.24324324 | G36: =F36-F32 -> -0.034534535 | H36: =SUM(D36:D39) -> 198 | I36: =SUM(E36:E39) -> 68
B37: Соболев | D37: 84 | E37: 36 | F37: =E37/D37*100% -> 0.42857143 | G37: =F37-F33 -> 0.17050691
B38: Россинский | D38: 37 | E38: 17 | F38: =E38/D38*100% -> 0.45945946 | G38: =F38-F34 -> 0.085833086
B39: Федосеев | D39: 40 | E39: 6 | F39: =E39/D39*100% -> 0.15 | G39: =F39-F35 -> -0.1664557 | J39: =AVERAGE(F39:F43) -> 0.34471195
B40: Багланова | C40: июнь | D40: 56 | E40: 24 | F40: =E40/D40*100% -> 0.42857143 | G40: =F40-F36 -> 0.18532819 | H40: =SUM(D40:D43) -> 256 | I40: =SUM(E40:E43) -> 102
B41: Соболев | D41: 88 | E41: 36 | F41: =E41/D41*100% -> 0.40909091 | G41: =F41-F37 -> -0.019480519
B42: Россинский | D42: 60 | E42: 28 | F42: =E42/D42*100% -> 0.46666667 | G42: =F42-F38 -> 0.0072072072
B43: Федосеев | D43: 52 | E43: 14 | F43: =E43/D43*100% -> 0.26923077 | G43: =F43-F39 -> 0.11923077
B44: Багланова | C44: июль | D44: 42 | E44: 16 | F44: =E44/D44*100% -> 0.38095238 | G44: =F44-F40 -> -0.047619048 | H44: =SUM(D44:D48) -> 364 | I44: =SUM(E44:E48) -> 92 | J44: =AVERAGE(F44:F48) -> 0.26654148
B45: Соболев | D45: 67 | E45: 16 | F45: =E45/D45*100% -> 0.23880597 | G45: =F45-F41 -> -0.17028494
B46: Россинский | D46: 95 | E46: 24 | F46: =E46/D46*100% -> 0.25263158 | G46: =F46-F42 -> -0.21403509
B47: Фёдорова | D47: 70 | E47: 19 | F47: =E47/D47*100% -> 0.27142857 | G47: =F47-F43 -> 0.0021978022
B48: Федосеев | D48: 90 | E48: 17 | F48: =E48/D48*100% -> 0.18888889 | G48: =F48-F44 -> -0.19206349
B49: Багланова | C49: август | D49: 46 | E49: 4 | F49: =E49/D49*100% -> 0.086956522 | G49: =F49-F45 -> -0.15184945 | H49: =SUM(D49:D53) -> 411 | I49: =SUM(E49:E53) -> 80 | J49: =AVERAGE(F49:F53) -> 0.20139817
B50: Соболев | D50: 149 | E50: 18 | F50: =E50/D50*100% -> 0.12080537 | G50: =F50-F46 -> -0.13182621
B51: Россинский | D51: 72 | E51: 8 | F51: =E51/D51*100% -> 0.11111111 | G51: =F51-F47 -> -0.16031746
B52: Фёдорова | D52: 67 | E52: 20 | F52: =E52/D52*100% -> 0.29850746 | G52: =F52-F48 -> 0.10961857
B53: Федосеев | D53: 77 | E53: 30 | F53: =E53/D53*100% -> 0.38961039 | G53: =F53-F48 -> 0.2007215
B54: Багланова | C54: сентябрь
B55: Соболев
B56: Россинский
B57: Федосеев | M57: конверсия из сд в оплату %
B58: Багланова | C58: октябрь | M58: =AVERAGE(J20:J69) -> 0.29540211
B59: Соболев
B60: Россинский
B61: Федосеев
B62: Багланова | C62: ноябрь
B63: Соболев
B64: Россинский
B65: Федосеев
B66: Багланова | C66: декабрь
B67: Соболев
B68: Россинский
B69: Федосеев
B70: Всего сделок | D70: =SUM(D20:D69) -> 2590
B71: Успешные сделки | E71: =SUM(E20:E69) -> 750
B72: Сделки в работе
B73: Неусп.сделки | F73: =D70-E71-E72 -> 1840
B74: Ср.колич сд в мес | C74: =AVERAGE(H20:H53) -> 323.75
B75: Ср.колич Усп. Сд/ мес | C75: =AVERAGE(I20:I69) -> 93.75

Sheet конверсия
B2: Самая низкая конверсия | C2: 0.253 | D2: июль | E2: Успешные сделки 92шт | F2: 2 человека были в отпуске Соболев/Багланова
C3: Источники | D3: количество | E3: причина отвала | F3: Этап отвала
C4: свой контакт | D4: 22
C5: звонок | D5: 23
C6: холодный обзвон | D6: 2
C7: мероприятия Форус | D7: 1
C8: успешная регистрация | D8: 46 | E8: неверный номер, клиент не РФ, проходил обучение, НДЗ, случ оставил заявку, отказ от перехода на 1С Фреш , работает с др.партнером по 1С | F8: Необработанные, уточнить потребности
C9: сайт итс | D9: 5
C10: по рекомендации | D10: 7
C11: срм форма | D11: 11
C12: лендинг 1С (Елизавета Бакелова) | D12: 1
C13: квиз | D13: 3
C14: авито | D14: 5
C15: регулярная сделка(Возврат Фреш, КП + продление каспера) | D15: 35 | E15: дубль,1с не пользуется , подключили тестовый, финанс.сложн,приостановка деятельности, перешли на аутсорс, ушел к др.партнеру, проблемы с согласованием | F15: необработанные, контроль сделки , отправить счет
B18: Самая высокая конверсия | C18: 0.39 | D18: июнь | E18: Успешные сделки 102
B19: Комментарий | C19: Источники | D19: количество | E19: сумма | F19: Продукты | G19: Лидирующий Сегмент | I19: Торговля прочая | J19: Услуги. Перевозки, логистика, склад | K19: Торговля продукты питания
C20: свой контакт | D20: 23 | E20: 304777 | G20: 1. Торговля прочая 2.Перевозки/логистика/склад 3. Торговля продукты питания | H20: Сделки | I20: 18 | J20: 14 | K20: 11
B21: ПП 1С, КП, Фреш - главный продуктовый драйвер | C21: звонок | D21: 43 | E21: 1067378 | F21: продления Соболев М, ФН, часы ЛК, 1С лицензии, КП, Фреш | H21: Выручка | I21: 473114 | J21: 341620 | K21: 239394
C22: холодный обзвон | D22: 1 | E22: 15334 | H22: Ср.чек | I22: 26284 | J22: 24401 | K22: 21763
C23: Форус.Биллинг | D23: 2 | E23: 10980
C24: мероприятия Форус | D24: 0
C25: визит в офис | D25: 5 | E25: 29700 | F25: Фреш базовый, рутокен
C26: агент | D26: 4 | E26: 120124
C27: Другое | D27: 5 | E27: 162800
C28: успешная регистрация | D28: 0
C29: сайт итс | D29: 3 | E29: 76600
B30: сделок в 5 раз меньше, но по деньгам принесли больше вх.звонков. Подумать как можно развивать источник | C30: по рекомендации | D30: 9 | E30: 1178520 | F30: продажа лицензий ЕРП - 1 большая
C31: срм форма | D31: 5 | E31: 140800
C32: лендинг 1С | D32: 0
C33: квиз УНФ | D33: 0
C34: авито | D34: 0
C35: регулярная сделка(Возврат Фреш, КП + продление каспера) | D35: 0
D36: =SUM(D20:D35) -> 100 | E36: =SUM(E20:E35) -> 3107013
A38: 46235
E40: Заполнение CRM-формы "ЦП. Контактные данные открытых линий" | F40: дата создания | G40: дата первого контакта МПП | I40: Заполнение CRM-формы "Внедрение и поддержка 1С:ЭПД" | J40: дата создания | K40: дата первого контакта МПП
F41: 46238.443 | G41: 46238.5 | J41: 46239.548 | K41: 46240.4
F42: 46238.668 | G42: 46238.672 | J42: 46244.958 | K42: 46245.509
F43: 46239.658 | G43: 46239.658 | J43: 46245.503 | K43: 46245.548
F44: 46240.424 | G44: 46240.503 | J44: 46251.523 | K44: 46251.691
F45: 46244.645 | G45: 46244.658 | J45: 46251.552
F46: 46245.711 | G46: 46245.731 | J46: 46252.469 | K46: 46252.592
F47: 46253.003 | G47: 46253.691 | J47: 46252.919 | K47: 46255.704
F48: 46253.56 | G48: 46253.57 | J48: 46253.185 | K48: 46254.696
F49: 46256.556 | G49: 46258.414 | J49: 46253.747 | K49: 46255.717
F50: 46259.465 | G50: 46259.48 | J50: 46254.008 | K50: 46258.712
F51: 46259.864 | G51: 46260.641 | J51: 46254.667 | K51: 46258.713
F52: 46260.377 | G52: 46260.378 | J52: 46255.184 | K52: 46259.59
J53: 46258.185 | K53: 46258.623
J54: 46258.828 | K54: 46259.558
J55: 46258.832
J56: 46259.419 | K56: 46259.443
J57: 46259.801
A59: Заявка с сайта - 1С-ЭПД | Обмен электронными перевозочными документами | Цена | B59: дата создания | C59: дата первого контакта МПП
B60: 46241.326 | C60: 46244.423
B61: 46244.665 | C61: 46244.665
B62: 46251.582 | C62: 46251.651
B63: 46253.472 | C63: 46255.451
B64: 46253.683 | C64: 46253.756
B65: 46258.311 | C65: 46259.441
B67: Самая низкая конверсия | C67: 0.2 | D67: август | E67: Успешные сделки 83шт | F67: в отвале 141 шт | G67: 188 сделок в работе по Б24
C68: Источники | D68: количество | E68: причина отвала | F68: Этап отвала | I68: Названия строк | J68: Сумма по полю Количество
C69: свой контакт | I69: Возврат документов | J69: 1
C70: звонок | I70: Задача/ЛПР/Бюджет/Сроки | J70: 4
C71: холодный обзвон | I71: Заказать | J71: 4
C72: мероприятия Форус | I72: Контроль оплаты | J72: 127
C73: успешная регистрация | I73: Контроль сделки | J73: 22
C74: сайт итс | I74: Необработанные | J74: 17
C75: по рекомендации | I75: Обсуждение сделки | J75: 20
C76: срм форма | I76: Оплачено | J76: 28
C77: лендинг 1С (Елизавета Бакелова) | I77: Отгрузка/Оформление в сервисе | J77: 2
C78: квиз | I78: Отправить КП/cчёт | J78: 2
C79: авито | I79: Отправить счет / договор | J79: 4
C80: регулярная сделка(Возврат Фреш, КП + продление каспера) | I80: Отправить счет/договор | J80: 3
I81: Оформить подписку / отгрузка | J81: 1
I82: Подготовка КП | J82: 1
I83: Презентация
I84: Уточнить потребности | J84: 2
I85: Уточнить потребности / Дать тест. доступ | J85: 5
I86: Общий итог | J86: 243

Sheet РК ЭПД
A1: 46235
A2: РК ЭПД | D2: Среднее фактическое время ожидания составило 13 ч 57 мин рабочего времени, медианное — 10 ч 34 мин. Исключила выходные и нерабочее время
A3: ЭПД Квиз | B3: дата создания | C3: дата первого контакта МПП | D3: Показатель | E3: Результат | G3: Показатель | H3: Квиз ЭПД | I3: Открытые линии | J3: 1С:ЭПД
B4: 46244.683 | C4: 46245.475 | D4: Количество заявок | E4: 9 | G4: Всего заявок | H4: 9 | I4: 12 | J4: 17
B5: 46246.862 | C5: 46248.638 | D5: Среднее время реакции | E5: 13 ч 57 мин | G5: Среднее время реакции | H5: 13 ч 57 мин | I5: 1 ч 38 мин | J5: 11 ч 08 мин
B6: 46247.085 | C6: 46248.713 | D6: Медиана | E6: 10 ч 34 мин | G6: Медиана | H6: 10 ч 34 мин | I6: 24 мин | J6: 5 ч 42 мин
B7: 46251.884 | C7: 46253.66 | D7: Минимальное время | E7: 4 ч 01 мин | G7: В пределах 1 рабочего часа | H7: 0 | I7: 0.667 | J7: 0.071
B8: 46252.804 | C8: 46253.744 | D8: Максимальное время | E8: 36 ч 15 мин | G8: В пределах рабочего дня | H8: 0.333 | I8: 1 | J8: 57,1%*
B9: 46253.835 | C9: 46255.44 | D9: Обработано в пределах 1 часа | E9: 0 из 9 | G9: Нет первого контакта | H9: Нет данных | I9: Нет | J9: 0.176
B10: 46254.526 | C10: 46255.573 | D10: Обработано в пределах 4 часов | E10: 0 из 9
B11: 46254.621 | C11: 46260.631 | D11: Обработано в пределах одного рабочего дня, до 9 часов | E11: 3 из 9 — 33,3%
B12: 46255.753 | C12: 46258.684 | D12: Ожидали более двух рабочих дней, свыше 18 часов | E12: 1 из 9 — 11,1%
B13: 46261.622 | C13: 46266.393 | D13: Ожидали более двух рабочих дней, свыше 18 часов | E13: 1 из 9 — 11,1%
B14: 46265.471 | C14: 46387.5
A16: 8 из 11 | B16: Валидность | C16: =8/11*100% -> 0.72727273
B17: Конверсия из лида в сделку | C17: =3/11*100% -> 0.27272727
B18: Конверсия из сделки в оплату | C18: 0
B19: Ожидаем оплаты | C19: 2 оплаты на 5400
A22: Заполнение CRM-формы "ЦП. Контактные данные открытых линий" | B22: дата создания | C22: дата первого контакта МПП | D22: С учётом только рабочих часов — будни, 09:00–18:00 — среднее время до первого контакта составляет 1 ч 38 мин, а медианное — всего 24 минуты
B23: 46238.443 | C23: 46238.5 | D23: Показатель | E23: Значение
B24: 46238.668 | C24: 46238.672 | D24: Количество заявок | E24: 12
B25: 46239.658 | C25: 46239.658 | D25: Среднее время реакции | E25: 1 ч 38 мин
B26: 46240.424 | C26: 46240.503 | D26: Медианное время реакции | E26: 24 мин
B27: 46244.645 | C27: 46244.658 | D27: Минимальное время | E27: 1 мин
B28: 46245.711 | C28: 46245.731 | D28: Максимальное время | E28: 7 ч 35 мин
B29: 46253.003 | C29: 46253.691 | D29: Контакт до 15 минут | E29: 4 из 12 — 33,3%
B30: 46253.56 | C30: 46253.57 | D30: Контакт до 30 минут | E30: 7 из 12 — 58,3%
B31: 46256.556 | C31: 46258.414 | D31: Контакт до 1 часа | E31: 8 из 12 — 66,7%
B32: 46259.465 | C32: 46259.48 | D32: Контакт до 4 часов | E32: 10 из 12 — 83,3%
B33: 46259.864 | C33: 46260.641 | D33: Контакт в течение рабочего дня, до 9 часов | E33: 12 из 12 — 100%
B34: 46260.377 | C34: 46260.378 | D34: Заявки с ожиданием более рабочего дня | E34: 0
B35: 46261.544
B36: 46265.474
A38: 13 из 14 | B38: Валидность | C38: =13/14*100% -> 0.92857143
B39: Конверсия из лида в сделку | C39: =8/14*100% -> 0.57142857
A40: 24500 | B40: Конверсия из сделки в оплату | C40: =3/8*100% -> 0.375
B41: Ожидаем оплаты | C41: 2 оплаты на 58 800
A43: Заполнение CRM-формы "Внедрение и поддержка 1С:ЭПД" | B43: Дата создания | C43: Дата первого контакта МПП | D43: Показатель | E43: Значение
B44: 46239.548 | C44: 46240.4 | D44: Всего заявок | E44: 17
B45: 46244.958 | C45: 46245.509 | D45: Есть первый контакт | E45: 14 — 82,4%
B46: 46245.503 | C46: 46245.548 | D46: Нет первого контакта | E46: 3 — 17,6%
B47: 46251.523 | C47: 46251.691 | D47: Среднее время реакции | E47: 11 ч 08 мин
B48: 46251.552 | D48: Медианное время реакции | E48: 5 ч 42 мин
B49: 46252.469 | C49: 46252.592 | D49: Минимальное время реакции | E49: 35 мин
B50: 46252.919 | C50: 46255.704 | D50: Максимальное время реакции | E50: 26 ч 05 мин
B51: 46253.185 | C51: 46254.696 | D51: Контакт до 1 часа | E51: 1 из 14 — 7,1%
B52: 46253.747 | C52: 46255.717 | D52: Контакт до 4 часов | E52: 4 из 14 — 28,6%
B53: 46254.008 | C53: 46258.712 | D53: Контакт в пределах рабочего дня, до 9 часов | E53: 8 из 14 — 57,1%
B54: 46254.667 | C54: 46258.713 | D54: Контакт позже рабочего дня | E54: 6 из 14 — 42,9%
B55: 46255.184 | C55: 46259.59 | D55: Ожидание более 2 рабочих дней, свыше 18 часов | E55: 4 из 14 — 28,6%
B56: 46258.185 | C56: 46258.623
B57: 46258.828 | C57: 46259.558
B58: 46258.832
B59: 46259.419 | C59: 46259.443
B60: 46259.801 | C60: 46261.712
B61: 46261.731 | C61: 46261.752
B62: 46262.117 | C62: 46262.478
B63: 46262.611
B64: 46262.812 | C64: 46266.66
B65: 46265.158 | C65: 46262.478
B66: 46265.404 | C66: 46265.611
B67: 46265.424 | C67: 46265.599
A68: 18 из 24 | B68: Валидность | C68: =18/24*100% -> 0.75
B69: Конверсия из лида в сделку | C69: =6/24*100% -> 0.25 | D69: 6 сделок
B70: Конверсия из сделки в оплату | C70: 0
B71: Ожидаем оплаты | C71: 2 оплаты на 19 500
A73: Заявка с сайта - 1С-ЭПД | Обмен электронными перевозочными документами | Цена | B73: дата создания | C73: дата первого контакта МПП | D73: Показатель | E73: Значение
B74: 46241.326 | C74: 46244.423 | D74: Всего заявок | E74: 6
B75: 46244.665 | C75: 46244.665 | D75: Среднее время реакции | E75: 6 ч 55 мин
B76: 46251.582 | C76: 46251.651 | D76: Медианное время реакции | E76: 5 ч 54 мин
B77: 46253.472 | C77: 46255.451 | D77: Минимальное время | E77: 1 мин
B78: 46253.683 | C78: 46253.756 | D78: Максимальное время | E78: 17 ч 30 мин
B79: 46258.311 | C79: 46259.441 | D79: Контакт до 15 минут | E79: 1 из 6 — 16,7%
B80: 46265.644 | C80: 46265.652 | D80: Контакт до 1 часа | E80: 1 из 6 — 16,7%
A81: 7 из 7 | B81: Валидность | C81: 1 | D81: Контакт до 4 часов | E81: 3 из 6 — 50%
B82: Конверсия из лида в сделку | C82: 1 | D82: Контакт в пределах рабочего дня, до 9 часов | E82: 3 из 6 — 50%
A83: 15000 | B83: Конверсия из сделки в оплату | C83: =3/7*100% -> 0.42857143 | D83: Контакт позже одного рабочего дня | E83: 3 из 6 — 50%
B84: Ожидаем 2 оплаты | C84: 3400
D87: Без контакта | E87: Среднее время | F87: Медиана | G87: До 1 часа | H87: До 4 часов | I87: В пределах смены, до 9 ч | J87: Максимум | N87: Наблюдения : | O87: часовой пояс наш (есть денег на Урале, Дальнем Восток, Камчатка, Красноярск, Новосиб)
D88: 0 | E88: 1 ч 38 мин | F88: 25 мин | G88: 0.667 | H88: 0.833 | I88: 1 | J88: 7 ч 35 мин | O88: Нет денег: Омск(общение с клиентами, до 50 тыс нет), Удмуртия (Ижевск), Бурятия, Улан-Удэ, Забайкальский край
D89: 0 | E89: 6 ч 55 мин | F89: 5 ч 55 мин | G89: 0.167 | H89: 0.5 | I89: 0.5 | J89: 17 ч 30 мин
D90: 3 | E90: 11 ч 08 мин | F90: 5 ч 42 мин | G90: 0.071 | H90: 0.286 | I90: 0.571 | J90: 26 ч 05 мин
D91: 0 | E91: 13 ч 57 мин | F91: 10 ч 34 мин | G91: 0 | H91: 0 | I91: 0.333 | J91: 36 ч 15 мин
D92: 3 | E92: 8 ч 21 мин | F92: 5 ч 27 мин | G92: 0.244 | H92: 0.415 | I92: 0.634 | J92: 36 ч 15 мин
A94: Рейтинг источников
A95: Место | B95: Источник | C95: Оценка процесса
A96: 1 | B96: Открытые линии | C96: Быстрая и стабильная обработка
A97: 2 | B97: Сайт 1С:ЭПД — цена | C97: Средняя скорость, есть существенные задержки
A98: 3 | B98: Внедрение и поддержка 1С:ЭПД | C98: Нестабильная обработка и заявки без контакта
A99: 4 | B99: Квиз ЭПД | C99: Критически медленная реакция

Sheet планы ЭПД
A1: 46235
A2: Менеджер | B2: План на период (шт.) | C2: Факт оплаченных сделок (шт.) | D2: Факт выручка (руб.) | E2: Выполнение плана (%)
A3: Фёдорова Н | B3: 5 | C3: 8 | D3: 35100 | E3: 1.6
A4: Багланова Т | B4: 4 | C4: 5 | D4: 20000 | E4: 1.25
A5: Россинский | B5: 5 | C5: 5 | D5: 49900 | E5: 1
A6: Соболев М | B6: 5 | C6: 12 | D6: 40200 | E6: 2.4
A7: Федосеев М | B7: 3 | C7: 7 | D7: 39500 | E7: 2.3333
A8: Итого | B8: 22 | C8: 37 | D8: 184700 | E8: 1.7167
A10: 46266
A11: Менеджер | B11: План на период (шт.) | C11: Факт оплаченных сделок (шт.) | D11: Факт выручка (руб.) | E11: Выполнение плана (%)
A12: Фёдорова Н | B12: 10
A13: Багланова Т | B13: 10
A14: Россинский | B14: 10
A15: Соболев М | B15: 10
A16: Федосеев М | B16: 7
A17: Итого | B17: =SUM(B12:B16) -> 47 | C17: =SUM(C12:C16) -> 0 | D17: =SUM(D12:D16) -> 0

Sheet Отпуска
A1: ID | B1: ФИО | C1: Отпуск (дней в год) | D1: Отпуск (использовано) | E1: Отпуск (остаток) | F1: Следующий отпуск (план) | G1: Больничные (дней в год) | H1: Опоздания (в мес)
A2: 1 | B2: Россинский Вадим Олегович | C2: 36 | H2: 0
A3: 2 | B3: Федосеев Максим Андреевич | C3: 36 | F3: 31.08 - 14.08
F4: 23.11 - 27.11 | H4: 0
A5: 3 | B5: Фёдорова Анастасия Андреевна | C5: 36 | G5: 3 | H5: 0
A6: 4 | B6: Багланова Антонина Михайловна | C6: 36 | F6: - | H6: 0
A7: 5 | B7: Соболев Максим Андреевич | C7: 36 | F7: - | H7: 0
A8: 6 | B8: Савинская Евгения Николаевна | C8: 36 | F8: 10.09 - 24.09

Sheet контроль лидов Б24
A1: Дата создания | B1: Время создания | C1: Время взятия в работу | D1: ID | E1: Стадия лида | F1: есть ли сделка | G1: источник | H1: Комментарии | I1: оплата | J1: Конверсия из лида в сделку | K1: Из сделки в оплату
A2: 46267 | B2: 0.65069444 | C2: 0.70833333 | D2: 268409 | E2: оценка готовности к покупке | F2: 0 | G2: сайт ИТС | H2: отправили кп | J2: =2/11*100% -> 0.18181818 | K2: =1/2*100% -> 0.5
A3: 46267 | B3: 0.66388889 | C3: 0.66388889 | D3: 268370 | E3: автозабраковка | F3: 0 | G3: вход.звонок | H3: хотели восстановить текущую 1С, покупали не у нас
A4: 46267 | D4: 268363 | E4: автозабраковка (повторный лид) | F4: 0 | H4: письмо на почту срм форус, актуальная сделка https://crm.forus.ru/crm/deal/details/317388/
A5: 46267 | B5: 0.61666667 | C5: 0.62708333 | D5: 268319 | E5: не заинтересовало наше предложение | F5: 0 | G5: Квиз УНФ | H5: ошибочно оставили заявка
A6: 46267 | B6: 0.61597222 | D6: 268317 | E6: автозабраковка, покупка текущая | F6: 1 | G6: Входящий звонок | H6: клиент Максима Федосеева, уже покупали ранее у нас , отработала | I6: 3660
A7: 46267 | B7: 0.54305556 | C7: 0.56111111 | D7: 268257 | E7: лид сконвертирован | F7: 1 | G7: CRM-форма | H7: продажа лицензий 1с
A8: 46267 | B8: 0.52152778 | D8: 268248 | E8: автозабраковка/общие вопросы | F8: 0 | G8: Входящий звонок | H8: нужно создать сделку, просили счет на лицензии фитнес
A9: 46267 | B9: 10:34 | D9: 268195 | E9: автозабраковка /обращение поставщика | F9: 0 | G9: Входящий звонок | H9: Являются партнерами 1С. Нужно было проконсультировать оформления апгрейда как партнера. Продиктовала номер телефона ЦРД
A10: 46267 | B10: 0.38819444 | D10: 268164 | E10: НДЗ более 3х раз | F10: 0 | G10: Входящий звонок | H10: вопрос по ТО(ТСД) , бюджет до 35 тыс
A11: 46267 | B11: 0.30555556 | D11: 268154 | E11: новое обращение | G11: Квиз УНФ | H11: не взяли в работу
A12: 46267 | B12: 0.0090277778 | D12: 268152 | E12: новое обращение | G12: квиз УНФ | H12: квиз был на Максе С , он не взял в работу вчера, сегодня перевела на Вадима
A13: 46268
A14: 46268
A15: 46268
A16: 46268
